iprestrict/__init__.py
iprestrict/admin.py
iprestrict/decorators.py
iprestrict/geoip.py
iprestrict/ip_utils.py
iprestrict/management/__init__.py
iprestrict/management/commands/__init__.py
iprestrict/management/commands/_utils.py
iprestrict/management/commands/add_ip_to_group.py
iprestrict/management/commands/import_rules.py
iprestrict/management/commands/importrules.py
iprestrict/management/commands/reload_rules.py
iprestrict/management/commands/reloadrules.py
iprestrict/middleware.py
iprestrict/migrations/0001_initial.py
iprestrict/migrations/0002_initial_data.py
iprestrict/migrations/0003_add_ipgroup_types.py
iprestrict/migrations/0004_add_iplocation.py
iprestrict/migrations/0005_add_reverse_ipgroup.py
iprestrict/migrations/0006_auto_20161013_1327.py
iprestrict/migrations/0007_iprange_description.py
iprestrict/migrations/__init__.py
iprestrict/models.py
iprestrict/restrictor.py
iprestrict/static/css/test_rules.css
iprestrict/static/javascript/lib/handlebars.min.js
iprestrict/static/javascript/lib/jquery-min.js
iprestrict/templates/404.html
iprestrict/templates/iprestrict/test_rules.html
iprestrict/urls.py
iprestrict/views.py
django_iprestrict_redux-1.9.0.dist-info/LICENSE
django_iprestrict_redux-1.9.0.dist-info/WHEEL
django_iprestrict_redux-1.9.0.dist-info/METADATA
django_iprestrict_redux-1.9.0.dist-info/RECORD
